PathPlanning/AStarRosetta.py
PathPlanning/__init__.py
path_planning_kholysa-0.0.8.dist-info/LICENSE
path_planning_kholysa-0.0.8.dist-info/METADATA
path_planning_kholysa-0.0.8.dist-info/WHEEL
path_planning_kholysa-0.0.8.dist-info/top_level.txt
path_planning_kholysa-0.0.8.dist-info/RECORD
