Metadata-Version: 2.1
Name: path-planning-kholysa
Version: 0.0.8
Summary: A package using the A* algorithm to plan a path for a quadcopter
Home-page: UNKNOWN
Author: Saif Elkholy
Author-email: saif.elkholy@mail.mcgill.com
License: UNKNOWN
Platform: UNKNOWN
Classifier: Programming Language :: Python :: 3
Classifier: License :: OSI Approved :: MIT License
Classifier: Operating System :: OS Independent
